desktopography/__init__.py
desktopography/cli.py
desktopography/crawler.py
desktopography/db.py
desktopography/desktops.py
desktopography/selector.py
desktopography/utils.py
desktopography-2.0.dist-info/LICENSE
desktopography-2.0.dist-info/METADATA
desktopography-2.0.dist-info/WHEEL
desktopography-2.0.dist-info/entry_points.txt
desktopography-2.0.dist-info/RECORD
