Metadata-Version: 2.1
Name: desktopography
Version: 2.0
Summary: Desktopography command line
Home-page: https://gitlab.com/fbochu/desktopography
License: BSD
Keywords: desktopography,wallpapers
Author: Fabien Bochu
Author-email: fabien.bochu+desktopography@nenio.xyz
Requires-Python: >=3.10,<4.0
Classifier: Development Status :: 4 - Beta
Classifier: Environment :: X11 Applications
Classifier: Intended Audience :: End Users/Desktop
Classifier: License :: OSI Approved :: BSD License
Classifier: License :: Other/Proprietary License
Classifier: Programming Language :: Python
Classifier: Programming Language :: Python :: 3
Classifier: Programming Language :: Python :: 3.10
Classifier: Programming Language :: Python :: 3.11
Classifier: Programming Language :: Python :: 3.12
Classifier: Topic :: Desktop Environment
Classifier: Topic :: Utilities
Requires-Dist: beautifulsoup4 (>=4.11.1,<5.0.0)
Requires-Dist: click (>=8.1.3,<9.0.0)
Requires-Dist: daiquiri (>=3.2.1,<4.0.0)
Requires-Dist: requests (>=2.28.1,<3.0.0)
Project-URL: Repository, https://gitlab.com/fbochu/desktopography
